x25519/__init__.py
x25519/djbec.py
x25519-0.0.2.dist-info/METADATA
x25519-0.0.2.dist-info/WHEEL
x25519-0.0.2.dist-info/top_level.txt
x25519-0.0.2.dist-info/RECORD
