Metadata-Version: 2.1
Name: x25519
Version: 0.0.2
Summary: A pure Python implemention of curve25519
Home-page: https://github.com/1ocalhost/x25519
Author: 1ocalhost
License: UNKNOWN
Platform: UNKNOWN
Classifier: Programming Language :: Python
Classifier: License :: Public Domain
Classifier: Operating System :: OS Independent
